embedmodel/__init__.py
embedmodel/embed_base.py
embed_base_model-0.1.1.dist-info/LICENSE
embed_base_model-0.1.1.dist-info/METADATA
embed_base_model-0.1.1.dist-info/WHEEL
embed_base_model-0.1.1.dist-info/top_level.txt
embed_base_model-0.1.1.dist-info/RECORD
