Metadata-Version: 2.1
Name: embed-base-model
Version: 0.1.1
Summary: Python abstract class for embedding sentences
Home-page: https://github.com/asulikeit/embed-base-model
Author: Daniel Lee
Author-email: rootuser.kr@gmail.com
License: Apache-2.0
Platform: UNKNOWN
Classifier: Programming Language :: Python :: 3
Classifier: License :: OSI Approved :: Apache Software License
Classifier: Operating System :: OS Independent
License-File: LICENSE
